lambdata_AM_art/__init__.py
lambdata_AM_art/df_utils.py
AM_Art021-0.0.1.dist-info/LICENSE
AM_Art021-0.0.1.dist-info/METADATA
AM_Art021-0.0.1.dist-info/WHEEL
AM_Art021-0.0.1.dist-info/top_level.txt
AM_Art021-0.0.1.dist-info/RECORD
